PySpace2/__init__.py
PySpace2/interface.py
PySpace2/databases/mpc_comets.db
PySpace2/kernels/lsk/naif0012.tls
PySpace2/kernels/pck/gm_de431.tpc
PySpace2/kernels/pck/pck00010.tpc
PySpace2/kernels/spk/de432s.bsp
PySpace2/planets/__init__.py
PySpace2/planets/comets.py
PySpace2/planets/earth.py
PySpace2/planets/first_kepler.py
PySpace2/planets/maps.py
PySpace2/planets/orbit.py
PySpace2/planets/phase_angel.py
PySpace2/planets/solar_system.py
PySpace2/planets/venus.py
PySpace2/utilities/__init__.py
PySpace2/utilities/constants.py
PySpace2/utilities/kernels_constants.py
PySpace2/utilities/kernels_utilities.py
PySpace2/utilities/utilities.py
PySpace2-0.5.2.dist-info/METADATA
PySpace2-0.5.2.dist-info/WHEEL
PySpace2-0.5.2.dist-info/top_level.txt
PySpace2-0.5.2.dist-info/RECORD
