Metadata-Version: 2.1
Name: PySpace2
Version: 0.5.2
Summary: Python package for astronomical calculations
Author-email: Patryk Niczke <kyrtap1301@gmail.com>
Requires-Python: >=3.9
Requires-Dist: numpy>=2.0.2
Requires-Dist: scipy>=1.13.1
Requires-Dist: matplotlib>=3.9.2
Requires-Dist: pandas>=2.2.3
Requires-Dist: sympy>=1.13.3
Requires-Dist: spiceypy
Requires-Dist: requests>=2.32.3
